rgd_imagery/__init__.py
rgd_imagery/apps.py
rgd_imagery/filters.py
rgd_imagery/large_image_utilities.py
rgd_imagery/signals.py
rgd_imagery/urls.py
rgd_imagery/views.py
rgd_imagery/admin/__init__.py
rgd_imagery/admin/annotation.py
rgd_imagery/admin/base.py
rgd_imagery/admin/processed.py
rgd_imagery/admin/raster.py
rgd_imagery/management/commands/_data_helper.py
rgd_imagery/management/commands/rgd_imagery_demo.py
rgd_imagery/management/commands/rgd_imagery_landsat_rgb_s3.py
rgd_imagery/migrations/0001_initial.py
rgd_imagery/migrations/0002_bandmeta_band_range.py
rgd_imagery/migrations/0003_remove_bandmeta_dtype.py
rgd_imagery/migrations/0004_auto_20210820_1212.py
rgd_imagery/migrations/0005_raster_extra_fields.py
rgd_imagery/migrations/0006_remove_imagemeta_number_of_bands.py
rgd_imagery/migrations/0007_auto_20210927_1501.py
rgd_imagery/migrations/0008_delete_kwcocoarchive.py
rgd_imagery/migrations/0009_alter_processedimage_processed_image.py
rgd_imagery/migrations/0010_alter_processedimage_ancillary_files_and_more.py
rgd_imagery/migrations/__init__.py
rgd_imagery/models/__init__.py
rgd_imagery/models/annotation.py
rgd_imagery/models/base.py
rgd_imagery/models/processed.py
rgd_imagery/models/raster.py
rgd_imagery/models/utility.py
rgd_imagery/rest/__init__.py
rgd_imagery/rest/tiles.py
rgd_imagery/rest/viewsets.py
rgd_imagery/serializers/__init__.py
rgd_imagery/serializers/base.py
rgd_imagery/serializers/processed.py
rgd_imagery/serializers/raster.py
rgd_imagery/stac/__init__.py
rgd_imagery/stac/constants.py
rgd_imagery/stac/tests.py
rgd_imagery/stac/urls.py
rgd_imagery/stac/views.py
rgd_imagery/stac/querysets/__init__.py
rgd_imagery/stac/querysets/collection.py
rgd_imagery/stac/querysets/item.py
rgd_imagery/stac/serializers/__init__.py
rgd_imagery/stac/serializers/collection.py
rgd_imagery/stac/serializers/collections.py
rgd_imagery/stac/serializers/conformance.py
rgd_imagery/stac/serializers/item.py
rgd_imagery/stac/serializers/items.py
django_rgd_imagery-0.3.11.dist-info/METADATA
django_rgd_imagery-0.3.11.dist-info/WHEEL
django_rgd_imagery-0.3.11.dist-info/top_level.txt
django_rgd_imagery-0.3.11.dist-info/RECORD
