Metadata-Version: 2.1
Name: django-rgd-imagery
Version: 0.3.11
Summary: UNKNOWN
Home-page: https://github.com/ResonantGeoData/ResonantGeoData
Author: Kitware, Inc.
Author-email: rgd@kitware.com
License: Apache 2.0
Platform: UNKNOWN
Classifier: Development Status :: 3 - Alpha
Classifier: Environment :: Web Environment
Classifier: Framework :: Django :: 3.0
Classifier: Framework :: Django
Classifier: Intended Audience :: Developers
Classifier: License :: OSI Approved :: Apache Software License
Classifier: Operating System :: OS Independent
Classifier: Programming Language :: Python :: 3
Classifier: Programming Language :: Python :: 3.8
Classifier: Programming Language :: Python
Requires-Python: >=3.8
Requires-Dist: bidict
Requires-Dist: django-large-image[colormaps] (>=0.8)
Requires-Dist: django-rgd (==0.3.11)
Requires-Dist: large-image (>=1.15)
Requires-Dist: large-image-source-gdal (>=1.15)
Requires-Dist: large-image-source-pil (>=1.15)
Requires-Dist: large-image-source-tiff (>=1.15)
Requires-Dist: numpy
Requires-Dist: pyvips
Requires-Dist: shapely
Requires-Dist: tifftools (>=1.2.0)
Provides-Extra: worker
Requires-Dist: large-image-converter ; extra == 'worker'
Requires-Dist: rasterio ; extra == 'worker'
